vaex/meta/__init__.py
vaex/meta/_version.py
vaex-4.17.0.dist-info/LICENSE.txt
vaex-4.17.0.dist-info/METADATA
vaex-4.17.0.dist-info/WHEEL
vaex-4.17.0.dist-info/top_level.txt
vaex-4.17.0.dist-info/RECORD
