Metadata-Version: 2.1
Name: vaex
Version: 4.17.0
Summary: Out-of-Core DataFrames to visualize and explore big tabular datasets
Home-page: https://www.github.com/vaexio/vaex
Author: Maarten A. Breddels
Author-email: maartenbreddels@gmail.com
License: MIT
Platform: UNKNOWN
